device_disconnector/__init__.py
device_disconnector/cli.py
device_disconnector/common.py
device_disconnector/version.py
device_disconnector-0.1.0.dist-info/LICENSE.txt
device_disconnector-0.1.0.dist-info/METADATA
device_disconnector-0.1.0.dist-info/WHEEL
device_disconnector-0.1.0.dist-info/entry_points.txt
device_disconnector-0.1.0.dist-info/RECORD
