Metadata-Version: 2.1
Name: device-disconnector
Version: 0.1.0
Summary: Disconnect devices with REST calls to IP based Device Disconnector
Home-page: https://github.com/brainelectronics/device-disconnector
License: MIT
Author: brainelectronics
Author-email: info@brainelectronics.de
Requires-Python: >=3.9,<4.0
Classifier: Development Status :: 5 - Production/Stable
Classifier: Intended Audience :: Developers
Classifier: License :: OSI Approved :: MIT License
Classifier: Programming Language :: Python :: 3
Classifier: Programming Language :: Python :: 3.9
Classifier: Programming Language :: Python :: 3.10
Classifier: Programming Language :: Python :: 3.11
Classifier: Programming Language :: Python :: 3.12
Classifier: Programming Language :: Python :: 3.13
Classifier: Programming Language :: Python :: 3 :: Only
Classifier: Topic :: System :: Hardware :: Hardware Drivers
Requires-Dist: requests (>=2.10,<3.0)
Project-URL: Repository, https://github.com/brainelectronics/device-disconnector
